csvbro/app/__init__.py
csvbro/app/command_parser.py
csvbro/app/csv_loader.py
csvbro/app/dataframe_viewer.py
csvbro/app/json_exporter.py
csvbro/app/main.py
csvbro/app/pivot_table_creator.py
csvbro/app/ui.py
csvbro/app/where_clause_handler.py
csvbro-0.0.5.dist-info/METADATA
csvbro-0.0.5.dist-info/WHEEL
csvbro-0.0.5.dist-info/entry_points.txt
csvbro-0.0.5.dist-info/top_level.txt
csvbro-0.0.5.dist-info/RECORD
